bin2elf/__init__.py
bin2elf/cli.py
bin2elf-0.1.4.dist-info/METADATA
bin2elf-0.1.4.dist-info/WHEEL
bin2elf-0.1.4.dist-info/entry_points.txt
bin2elf-0.1.4.dist-info/licenses/LICENCE
bin2elf-0.1.4.dist-info/RECORD
