Metadata-Version: 2.4
Name: bin2elf
Version: 0.1.4
Summary: Convert a raw binary blob into a minimal ARM ELF at a chosen load address.
Project-URL: Homepage, https://github.com/TAbdiukov/bin2elf
Project-URL: Repository, https://github.com/TAbdiukov/bin2elf
Project-URL: Issues, https://github.com/TAbdiukov/bin2elf/issues
Author: Tim Abdiukov
License-Expression: Apache-2.0
License-File: LICENCE
Keywords: IDA,IDA Pro,IDAPython,arm,binutils,elf,firmware,ida-pro,reverse engineering
Classifier: Development Status :: 4 - Beta
Classifier: Environment :: Console
Classifier: Intended Audience :: Developers
Classifier: Intended Audience :: Science/Research
Classifier: Operating System :: MacOS
Classifier: Operating System :: MacOS :: MacOS X
Classifier: Operating System :: POSIX
Classifier: Operating System :: POSIX :: Linux
Classifier: Operating System :: POSIX :: Other
Classifier: Topic :: Security
Classifier: Topic :: Software Development :: Build Tools
Classifier: Topic :: Software Development :: Disassemblers
Requires-Python: >=3.7
